<root><promto><companies><company mask="M" prefix="M">MACCOMEVAP<types><type mask="" prefix="M">PRODUTOS ACABADOS<families><family mask="N" prefix="MN">AUXILIO A NAVEGACAO</family><family mask="C" prefix="MC">CAIXA</family><family mask="CO" prefix="MCO">CONDULETE</family><family mask="CP" prefix="MCP">CONTRA PORCA</family><family mask="HO" prefix="MHO">HOLOFOTE</family><family mask="L" prefix="ML">LUMINARIA</family><family mask="LAM" prefix="MLAM">LAMPADA</family><family mask="MO" prefix="MMO">MODULO PARA BOTAO</family><family mask="N" prefix="MN">AUXILIO A NAVEGACAO</family><family mask="P" prefix="MP">PROJETOR</family><family mask="PC" prefix="MPC">PRENSA CABO</family><family mask="PL" prefix="MPL">PLUGUE</family><family mask="PS" prefix="MPS">POSTE</family><family mask="TAC" prefix="MTAC">TOMADAS PARA ACOMODACOES</family><family mask="TO" prefix="MTO">TOMADA</family><family mask="TA" prefix="MTA">TAMPAO</family></families></type><type mask="R" prefix="MR">PRODUTOS REVENDA<families><family mask="L" prefix="MRL">LUMINARIA<models><model mask="AU" prefix="MRLAU">AUREON<code_list/><field_list/></model></models></family></families></type></types></company></companies></promto></root>
